sphinx_exec_directive/__init__.py
sphinx_exec_directive/plot_directive.py
sphinx_exec_directive-0.6.dist-info/LICENSE.txt
sphinx_exec_directive-0.6.dist-info/METADATA
sphinx_exec_directive-0.6.dist-info/WHEEL
sphinx_exec_directive-0.6.dist-info/top_level.txt
sphinx_exec_directive-0.6.dist-info/RECORD
