Metadata-Version: 2.1
Name: sphinx-exec-directive
Version: 0.6
Summary: Run Python code blocks and display the output directly within Sphinx documentation
Home-page: https://github.com/yongrenjie/sphinx-exec-directive
Author: Jonathan Yong
Author-email: yongrenjie@gmail.com
License: MIT
Platform: UNKNOWN
Classifier: Programming Language :: Python :: 3
Classifier: License :: OSI Approved :: MIT License
Classifier: Operating System :: OS Independent
Requires-Python: >=3.7
License-File: LICENSE.txt
Requires-Dist: docutils
